demo_py_package/__init__.py
demo_py_package/intro.py
demo_py_package-0.1.9.1.dist-info/LICENSE.txt
demo_py_package-0.1.9.1.dist-info/METADATA
demo_py_package-0.1.9.1.dist-info/WHEEL
demo_py_package-0.1.9.1.dist-info/top_level.txt
demo_py_package-0.1.9.1.dist-info/RECORD
